pstatx/__init__.py
pstatx/pstatx.py
pstatx-0.0.1.dist-info/LICENSE
pstatx-0.0.1.dist-info/METADATA
pstatx-0.0.1.dist-info/WHEEL
pstatx-0.0.1.dist-info/entry_points.txt
pstatx-0.0.1.dist-info/top_level.txt
pstatx-0.0.1.dist-info/RECORD
