Metadata-Version: 2.1
Name: pstatx
Version: 0.0.1
Summary: pstatx
Home-page: https://github.com/Nathalon/pstatx.git
Author: Nathalon
License: GPL v3
Platform: UNKNOWN
License-File: LICENSE
